whylogs_sketching.cpython-39-aarch64-linux-gnu.so
whylogs_sketching-3.4.1.dev3.dist-info/NOTICE
whylogs_sketching-3.4.1.dev3.dist-info/top_level.txt
whylogs_sketching-3.4.1.dev3.dist-info/LICENSE
whylogs_sketching-3.4.1.dev3.dist-info/METADATA
whylogs_sketching-3.4.1.dev3.dist-info/RECORD
whylogs_sketching-3.4.1.dev3.dist-info/WHEEL
