Metadata-Version: 2.1
Name: whylogs-sketching
Version: 3.4.1.dev3
Summary: sketching library of whylogs
Home-page: https://github.com/whylabs/whylogs-sketching
Author: whylogs team
Author-email: support@whylabs.ai
License: Apache License 2.0
License-File: LICENSE
License-File: NOTICE
